LICENSE.txt
README.txt
TODO.txt
setup.cfg
setup.py
setup_data.py
ETSProjectTools.egg-info/PKG-INFO
ETSProjectTools.egg-info/SOURCES.txt
ETSProjectTools.egg-info/dependency_links.txt
ETSProjectTools.egg-info/entry_points.txt
ETSProjectTools.egg-info/namespace_packages.txt
ETSProjectTools.egg-info/not-zip-safe
ETSProjectTools.egg-info/requires.txt
ETSProjectTools.egg-info/top_level.txt
docs/html.zip
docs/source/conf.py
docs/source/.static/rest.css
enthought/__init__.py
enthought/ets/__init__.py
enthought/ets/api.py
enthought/ets/argparse.py
enthought/ets/base_subcommand.py
enthought/ets/bdist.py
enthought/ets/checkout.py
enthought/ets/clean.py
enthought/ets/depends.py
enthought/ets/develop.py
enthought/ets/diff.py
enthought/ets/ets.py
enthought/ets/graph.py
enthought/ets/info.py
enthought/ets/install.py
enthought/ets/map.py
enthought/ets/pkg_url.py
enthought/ets/revert.py
enthought/ets/sdist.py
enthought/ets/status.py
enthought/ets/test.py
enthought/ets/update.py
enthought/ets/version.py
enthought/ets/tools/__init__.py
enthought/ets/tools/checkouts.py
enthought/ets/tools/project_set.py
enthought/ets/tools/tests/project_set_map_testcase.py
enthought/proxy/__init__.py
enthought/proxy/api.py
enthought/proxy/connect_HTTPS_handler.py
enthought/proxy/connect_HTTP_handler.py
enthought/proxy/util.py
enthought/proxy/tests/__init__.py
enthought/proxy/tests/https_connect.py
enthought/setuptools/__init__.py
enthought/setuptools/collector.py
enthought/setuptools/egg_db.py
enthought/setuptools/egg_db_command.py
enthought/setuptools/python_packages.py
enthought/setuptools/validate_deps.py
integrationtests/test.map